shapiq/__init__.py
shapiq/_deprecated_redirects.py
shapiq/_version.py
shapiq/game.py
shapiq/interaction_values.py
shapiq/py.typed
shapiq/typing.py
shapiq/approximator/__init__.py
shapiq/approximator/base.py
shapiq/approximator/sampling.py
shapiq/approximator/marginals/__init__.py
shapiq/approximator/marginals/owen.py
shapiq/approximator/marginals/stratified.py
shapiq/approximator/montecarlo/__init__.py
shapiq/approximator/montecarlo/base.py
shapiq/approximator/montecarlo/shapiq.py
shapiq/approximator/montecarlo/svarmiq.py
shapiq/approximator/permutation/__init__.py
shapiq/approximator/permutation/sii.py
shapiq/approximator/permutation/stii.py
shapiq/approximator/permutation/sv.py
shapiq/approximator/regression/__init__.py
shapiq/approximator/regression/base.py
shapiq/approximator/regression/faithful.py
shapiq/approximator/regression/kadd_shap.py
shapiq/approximator/regression/kernelshap.py
shapiq/approximator/regression/kernelshapiq.py
shapiq/approximator/sparse/__init__.py
shapiq/approximator/sparse/base.py
shapiq/approximator/sparse/proxyspex.py
shapiq/approximator/sparse/spex.py
shapiq/datasets/__init__.py
shapiq/datasets/_all.py
shapiq/datasets/data/adult_census.csv
shapiq/datasets/data/bike.csv
shapiq/datasets/data/california_housing.csv
shapiq/explainer/__init__.py
shapiq/explainer/agnostic.py
shapiq/explainer/base.py
shapiq/explainer/configuration.py
shapiq/explainer/custom_types.py
shapiq/explainer/tabpfn.py
shapiq/explainer/tabular.py
shapiq/explainer/utils.py
shapiq/explainer/validation.py
shapiq/explainer/product_kernel/__init__.py
shapiq/explainer/product_kernel/base.py
shapiq/explainer/product_kernel/conversion.py
shapiq/explainer/product_kernel/explainer.py
shapiq/explainer/product_kernel/game.py
shapiq/explainer/product_kernel/product_kernel.py
shapiq/explainer/product_kernel/validation.py
shapiq/explainer/tree/__init__.py
shapiq/explainer/tree/base.py
shapiq/explainer/tree/explainer.py
shapiq/explainer/tree/treeshapiq.py
shapiq-1.4.1.dist-info/licenses/LICENSE
shapiq-1.4.1.dist-info/METADATA
shapiq-1.4.1.dist-info/WHEEL
shapiq-1.4.1.dist-info/top_level.txt
shapiq-1.4.1.dist-info/RECORD
