Metadata-Version: 2.4
Name: shapiq
Version: 1.4.1
Summary: Shapley Interactions for Machine Learning
Author: Hubert Baniecki, Fabian Fumagalli
Author-email: Maximilian Muschalik <Maximilian.Muschalik@lmu.de>, "Santo M. A. R. Thies" <S.Thies@campus.lmu.de>
Maintainer-email: Maximilian Muschalik <Maximilian.Muschalik@lmu.de>, "Santo M. A. R. Thies" <S.Thies@campus.lmu.de>
License-Expression: MIT
Project-URL: documentation, https://shapiq.readthedocs.io
Project-URL: source, https://github.com/mmschlk/shapiq
Project-URL: tracker, https://github.com/mmschlk/shapiq/issues
Project-URL: changelog, https://github.com/mmschlk/shapiq/blob/main/CHANGELOG.md
Keywords: python,machine learning,interpretable machine learning,shap,xai,explainable ai,interaction,shapley interactions,shapley values,feature interaction
Classifier: Development Status :: 4 - Beta
Classifier: Intended Audience :: Developers
Classifier: Intended Audience :: Science/Research
Classifier: Topic :: Scientific/Engineering
Classifier: Topic :: Scientific/Engineering :: Artificial Intelligence
Classifier: Operating System :: Microsoft :: Windows
Classifier: Operating System :: Unix
Classifier: Operating System :: MacOS
Classifier: Programming Language :: Python :: 3
Classifier: Programming Language :: Python :: 3.10
Classifier: Programming Language :: Python :: 3.11
Classifier: Programming Language :: Python :: 3.12
Classifier: Programming Language :: Python :: 3.13
Requires-Python: >=3.10
License-File: LICENSE
Requires-Dist: numpy
Requires-Dist: scipy
Requires-Dist: pandas
Requires-Dist: joblib
Requires-Dist: scikit-learn
Requires-Dist: tqdm
Requires-Dist: requests
Requires-Dist: sparse-transform
Requires-Dist: galois
Requires-Dist: matplotlib
Requires-Dist: networkx
Requires-Dist: colour
Requires-Dist: pillow
Dynamic: license-file
